manojkanakam/__init__.py
manojkanakam/resume.py
manojkanakam/assets/Manoj Kanakam Resume.pdf
manojkanakam/assets/resume.pdf
manojkanakam-0.2.2.dist-info/licenses/LICENSE
manojkanakam-0.2.2.dist-info/METADATA
manojkanakam-0.2.2.dist-info/WHEEL
manojkanakam-0.2.2.dist-info/top_level.txt
manojkanakam-0.2.2.dist-info/RECORD
