Metadata-Version: 2.4
Name: manojkanakam
Version: 0.2.2
Summary: A simple package that downloads Manoj Kanakam's resume.
Author-email: Manoj Kanakam <manojkanakam9@gmail.com>
License: MIT License
Classifier: Programming Language :: Python :: 3
Classifier: License :: OSI Approved :: MIT License
Classifier: Operating System :: OS Independent
Requires-Python: >=3.8
License-File: LICENSE
Dynamic: license-file
